LICENSE
MANIFEST.in
README.rst
setup.cfg
setup.py
django_extrasettings.egg-info/PKG-INFO
django_extrasettings.egg-info/SOURCES.txt
django_extrasettings.egg-info/dependency_links.txt
django_extrasettings.egg-info/top_level.txt
extrasettings/__init__.py
extrasettings/admin.py
extrasettings/apps.py
extrasettings/models.py
extrasettings/static/.DS_Store
extrasettings/static/extrasettings/css/bootstrap-3.css
extrasettings/static/extrasettings/js/jQuery.js
extrasettings/static/extrasettings/js/jsoneditor.min.js
extrasettings/static/extrasettings/js/settings-edit.js