Metadata-Version: 1.1
Name: django-extrasettings
Version: 0.1
Summary: Admin-configurable Django settings
Home-page: https://github.com/pistacchio/django-extrasettings
Author: Gustavo Di Pietro
Author-email: pistacchio@gmail.com
License: MIT License
Platform: UNKNOWN
Classifier: Environment :: Web Environment
Classifier: Framework :: Django
Classifier: Intended Audience :: Developers
Classifier: License :: OSI Approved :: MIT License
Classifier: Operating System :: OS Independent
Classifier: Programming Language :: Python
Classifier: Programming Language :: Python :: 2.7
Classifier: Topic :: Internet :: WWW/HTTP
Classifier: Topic :: Internet :: WWW/HTTP :: Dynamic Content
